{
  "anvil_cost": 4,
  "description": {
    "translate": "enchantment.the_annihilation.poison"
  },
  "effects": {
    "minecraft:post_attack": [
      {
        "affected": "victim",
        "effect": {
          "type": "minecraft:apply_mob_effect",
          "to_apply": "poison",
          "min_amplifier": {
            "type": "minecraft:linear",
            "base": 0,
            "per_level_above_first": 1
          },
          "max_amplifier": {
            "type": "minecraft:linear",
            "base": 0,
            "per_level_above_first": 1
          },
          "min_duration": 6.25,
          "max_duration": 6.25
        },
        "enchanted": "attacker",
        "requirements": {
          "condition": "minecraft:damage_source_properties",
          "predicate": {
            "is_direct": true
          }
        }
      }
    ]
  },
  "exclusive_set": "#the_annihilation:exclusive_set/mob_effect",
  "max_cost": {
    "base": 60,
    "per_level_above_first": 20
  },
  "max_level": 2,
  "min_cost": {
    "base": 10,
    "per_level_above_first": 20
  },
  "slots": [
    "mainhand"
  ],
  "supported_items": "#minecraft:enchantable/sword",
  "weight": 2
}